pytoolsz_lnx/__init__.py
pytoolsz_lnx/utils.py
pytoolsz_lnx-0.1.3.dist-info/METADATA
pytoolsz_lnx-0.1.3.dist-info/WHEEL
pytoolsz_lnx-0.1.3.dist-info/licenses/LICENSE
pytoolsz_lnx-0.1.3.dist-info/RECORD
