Metadata-Version: 2.3
Name: pytoolsz-lnx
Version: 0.1.3
Summary: This is the Linux-optimized version of my Python toolkit, pytoolsz.
Author-email: Sidney Zhang <liangyi@me.com>
License: MulanPSL-2.0
Requires-Python: >=3.8
Requires-Dist: imapclient>=3.0.1
Requires-Dist: pendulum>=3.1.0
Requires-Dist: rich>=14.0.0
